SimplePyDB/__init__.py
SimplePyDB/database.py
SimplePyDB-1.0.0.dist-info/LICENSE
SimplePyDB-1.0.0.dist-info/METADATA
SimplePyDB-1.0.0.dist-info/WHEEL
SimplePyDB-1.0.0.dist-info/top_level.txt
SimplePyDB-1.0.0.dist-info/RECORD
