Metadata-Version: 2.1
Name: SimplePyDB
Version: 1.0.0
Summary: A Python package for managing a simple database structure
Author: CodeSoft
Classifier: License :: OSI Approved :: MIT License
Classifier: Programming Language :: Python :: 3
Classifier: Programming Language :: Python :: 3.6
Classifier: Programming Language :: Python :: 3.7
Classifier: Programming Language :: Python :: 3.8
License-File: LICENSE
